mark_mate/__init__.py
mark_mate/analyzers/__init__.py
mark_mate/analyzers/react_analysis.py
mark_mate/analyzers/static_analysis.py
mark_mate/analyzers/web_validation.py
mark_mate/cli/__init__.py
mark_mate/cli/consolidate.py
mark_mate/cli/extract.py
mark_mate/cli/generate_config.py
mark_mate/cli/grade.py
mark_mate/cli/main.py
mark_mate/cli/scan.py
mark_mate/config/__init__.py
mark_mate/config/defaults.py
mark_mate/config/grading_config.py
mark_mate/config/settings.py
mark_mate/core/__init__.py
mark_mate/core/analyzer.py
mark_mate/core/enhanced_grader.py
mark_mate/core/llm_provider.py
mark_mate/core/processor.py
mark_mate/core/prompt_manager.py
mark_mate/extractors/__init__.py
mark_mate/extractors/base_extractor.py
mark_mate/extractors/code_extractor.py
mark_mate/extractors/github_extractor.py
mark_mate/extractors/models.py
mark_mate/extractors/office_extractor.py
mark_mate/extractors/react_extractor.py
mark_mate/extractors/web_extractor.py
mark_mate/gui/__init__.py
mark_mate/gui/main.py
mark_mate/gui/adapters/__init__.py
mark_mate/gui/adapters/cli_adapter.py
mark_mate/gui/components/__init__.py
mark_mate/gui/components/header.py
mark_mate/gui/components/navigation.py
mark_mate/gui/pages/__init__.py
mark_mate/gui/pages/config.py
mark_mate/gui/pages/consolidate.py
mark_mate/gui/pages/extract.py
mark_mate/gui/pages/grade.py
mark_mate/gui/pages/scan.py
mark_mate/gui/utils/__init__.py
mark_mate/gui/utils/async_runner.py
mark_mate/gui/utils/progress_manager.py
mark_mate/utils/__init__.py
mark_mate/utils/encoding_utils.py
mark_mate/utils/file_detection.py
mark_mate-0.2.0.dist-info/licenses/LICENSE
mark_mate-0.2.0.dist-info/METADATA
mark_mate-0.2.0.dist-info/WHEEL
mark_mate-0.2.0.dist-info/entry_points.txt
mark_mate-0.2.0.dist-info/top_level.txt
mark_mate-0.2.0.dist-info/RECORD
