Metadata-Version: 2.4
Name: mark-mate
Version: 0.2.0
Summary: Your AI Teaching Assistant for Assignments and Assessment
Author-email: MarkMate Development Team <dev@markmate.ai>
License: MIT
Project-URL: Homepage, https://github.com/markmate-ai/mark-mate
Project-URL: Documentation, https://mark-mate.readthedocs.io
Project-URL: Repository, https://github.com/markmate-ai/mark-mate
Project-URL: Bug Reports, https://github.com/markmate-ai/mark-mate/issues
Keywords: education,grading,ai,assessment,teaching,automated-grading
Classifier: Development Status :: 4 - Beta
Classifier: Intended Audience :: Education
Classifier: Topic :: Education
Classifier: Topic :: Scientific/Engineering :: Artificial Intelligence
Classifier: License :: OSI Approved :: MIT License
Classifier: Programming Language :: Python :: 3
Classifier: Programming Language :: Python :: 3.9
Classifier: Programming Language :: Python :: 3.10
Classifier: Programming Language :: Python :: 3.11
Classifier: Programming Language :: Python :: 3.12
Requires-Python: >=3.9
License-File: LICENSE
Requires-Dist: PyPDF2>=3.0.0
Requires-Dist: python-docx>=1.1.0
Requires-Dist: markdown>=3.6.0
Requires-Dist: nbconvert>=7.16.0
Requires-Dist: python-pptx>=0.6.23
Requires-Dist: openpyxl>=3.1.2
Requires-Dist: pandas>=2.2.0
Requires-Dist: beautifulsoup4>=4.12.3
Requires-Dist: html5lib>=1.1
Requires-Dist: cssutils>=2.11.1
Requires-Dist: lxml>=5.1.0
Requires-Dist: requests>=2.31.0
Requires-Dist: litellm>=1.55.0
Requires-Dist: anthropic>=0.40.0
Requires-Dist: openai>=1.50.0
Requires-Dist: pyyaml>=6.0.1
Requires-Dist: pydantic>=2.0.0
Requires-Dist: flet>=0.21.0
Requires-Dist: matplotlib>=3.7.0
Provides-Extra: dev
Requires-Dist: pytest>=8.0.0; extra == "dev"
Requires-Dist: pytest-asyncio>=0.23.0; extra == "dev"
Requires-Dist: pytest-cov>=4.0.0; extra == "dev"
Requires-Dist: ruff>=0.6.0; extra == "dev"
Requires-Dist: basedpyright>=1.17.0; extra == "dev"
Provides-Extra: docs
Requires-Dist: mkdocs>=1.6.0; extra == "docs"
Requires-Dist: mkdocs-material>=9.5.0; extra == "docs"
Requires-Dist: mkdocstrings[python]>=0.25.0; extra == "docs"
Dynamic: license-file
